src/epos/__init__.py
src/epos/attributes.py
src/epos/constants.py
src/epos/document.py
src/epos/elements.py
src/epos/printer.py
src/epos/status.py
epos_print_xml-0.3.dist-info/METADATA
epos_print_xml-0.3.dist-info/WHEEL
epos_print_xml-0.3.dist-info/licenses/LICENSE
epos_print_xml-0.3.dist-info/RECORD
