Metadata-Version: 2.1
Name: ePos-Print-XML
Version: 0.3
Summary: Library to communicate with Epson thermal printers via ePOS-Print XML protocol
Project-URL: Homepage, https://github.com/MertenF/epos-print-xml
Project-URL: Bug Tracker, https://github.com/MertenF/epos-print-xml/issues
Author: Merten Fermont
License-File: LICENSE
Keywords: epos,printing,receipt,thermoprinter,voucher printer
Classifier: License :: OSI Approved :: MIT License
Classifier: Operating System :: OS Independent
Classifier: Programming Language :: Python :: 3
Classifier: Topic :: Office/Business :: Financial :: Point-Of-Sale
Classifier: Topic :: Software Development :: Libraries :: Python Modules
Requires-Python: >=3.10
Requires-Dist: requests
